{"title":"BBC News 코리아 ─ TOP 뉴스","url":"https://www.bbc.com/korean/popular/read","favicon":"https://static.files.bbci.co.uk/ws/simorgh-assets/public/korean/images/icons/icon-72x72.png","elements":[{"title":"우울하고 화나는 불편한 감정...왜 중요할까?","contents":"<div class=\"bbc-1k5dca0 emesykt1\"><div dir=\"ltr\" class=\"bbc-cco6mt erh4ywh3\"><span class=\"bbc-1kpt1ox erh4ywh0\">1</span></div><div dir=\"ltr\" class=\"bbc-1dy6y1w emesykt3\"><a href=\"/korean/features-59876813\" class=\"bbc-bta7jm emesykt4\">우울하고 화나는 불편한 감정...왜 중요할까?</a></div></div>","link":"https://www.bbc.com/korean/features-59876813","retrieved":1641402074926},{"title":"'감기 환자 절반, 오미크론 감염자일 가능성 있다'","contents":"<div class=\"bbc-1k5dca0 emesykt1\"><div dir=\"ltr\" class=\"bbc-cco6mt erh4ywh3\"><span class=\"bbc-1kpt1ox erh4ywh0\">2</span></div><div dir=\"ltr\" class=\"bbc-1dy6y1w emesykt3\"><a href=\"/korean/international-59790411\" class=\"bbc-bta7jm emesykt4\">'감기 환자 절반, 오미크론 감염자일 가능성 있다'</a></div></div>","link":"https://www.bbc.com/korean/international-59790411","retrieved":1641402074926},{"title":"방역 패스 3일부터 '유효기간' 적용...달라지는 것은?","contents":"<div class=\"bbc-1k5dca0 emesykt1\"><div dir=\"ltr\" class=\"bbc-cco6mt erh4ywh3\"><span class=\"bbc-1kpt1ox erh4ywh0\">3</span></div><div dir=\"ltr\" class=\"bbc-1dy6y1w emesykt3\"><a href=\"/korean/59807097\" class=\"bbc-bta7jm emesykt4\">방역 패스 3일부터 '유효기간' 적용...달라지는 것은?</a></div></div>","link":"https://www.bbc.com/korean/59807097","retrieved":1641402074926},{"title":"'오미크론, 이스라엘 집단면역 가져올 수도… 대가는 따라'","contents":"<div class=\"bbc-1k5dca0 emesykt1\"><div dir=\"ltr\" class=\"bbc-cco6mt erh4ywh3\"><span class=\"bbc-1kpt1ox erh4ywh0\">4</span></div><div dir=\"ltr\" class=\"bbc-1dy6y1w emesykt3\"><a href=\"/korean/international-59807508\" class=\"bbc-bta7jm emesykt4\">'오미크론, 이스라엘 집단면역 가져올 수도… 대가는 따라'</a></div></div>","link":"https://www.bbc.com/korean/international-59807508","retrieved":1641402074932},{"title":"중국 '작은 눈' 모델 논란...'눈 작다고 중국인 될 자격 없나요?'","contents":"<div class=\"bbc-1k5dca0 emesykt1\"><div dir=\"ltr\" class=\"bbc-cco6mt erh4ywh3\"><span class=\"bbc-1kpt1ox erh4ywh0\">5</span></div><div dir=\"ltr\" class=\"bbc-1dy6y1w emesykt3\"><a href=\"/korean/features-59807098\" class=\"bbc-bta7jm emesykt4\">중국 '작은 눈' 모델 논란...'눈 작다고 중국인 될 자격 없나요?'</a></div></div>","link":"https://www.bbc.com/korean/features-59807098","retrieved":1641402074932},{"title":"'여자 잡스' 테라노스 창업자, 결국 유죄 평결","contents":"<div class=\"bbc-1k5dca0 emesykt1\"><div dir=\"ltr\" class=\"bbc-cco6mt erh4ywh3\"><span class=\"bbc-1kpt1ox erh4ywh0\">6</span></div><div dir=\"ltr\" class=\"bbc-1dy6y1w emesykt3\"><a href=\"/korean/international-59866005\" class=\"bbc-bta7jm emesykt4\">'여자 잡스' 테라노스 창업자, 결국 유죄 평결</a></div></div>","link":"https://www.bbc.com/korean/international-59866005","retrieved":1641402074932},{"title":"프랑스, 과일·채소 플라스틱 포장 금지 시행","contents":"<div class=\"bbc-1k5dca0 emesykt1\"><div dir=\"ltr\" class=\"bbc-cco6mt erh4ywh3\"><span class=\"bbc-1kpt1ox erh4ywh0\">7</span></div><div dir=\"ltr\" class=\"bbc-1dy6y1w emesykt3\"><a href=\"/korean/international-59837819\" class=\"bbc-bta7jm emesykt4\">프랑스, 과일·채소 플라스틱 포장 금지 시행</a></div></div>","link":"https://www.bbc.com/korean/international-59837819","retrieved":1641402074932},{"title":"북한, 새해 첫 탄도미사일 발사… 속내는?","contents":"<div class=\"bbc-1k5dca0 emesykt1\"><div dir=\"ltr\" class=\"bbc-cco6mt erh4ywh3\"><span class=\"bbc-1kpt1ox erh4ywh0\">8</span></div><div dir=\"ltr\" class=\"bbc-1dy6y1w emesykt3\"><a href=\"/korean/news-59864972\" class=\"bbc-bta7jm emesykt4\">북한, 새해 첫 탄도미사일 발사… 속내는?</a></div></div>","link":"https://www.bbc.com/korean/news-59864972","retrieved":1641402074933},{"title":"10년간 최소 30명 월북... 탈북민들 국경 두번 넘는 이유는?","contents":"<div class=\"bbc-1k5dca0 emesykt1\"><div dir=\"ltr\" class=\"bbc-cco6mt erh4ywh3\"><span class=\"bbc-1kpt1ox erh4ywh0\">9</span></div><div dir=\"ltr\" class=\"bbc-1dy6y1w emesykt3\"><a href=\"/korean/news-59856610\" class=\"bbc-bta7jm emesykt4\">10년간 최소 30명 월북... 탈북민들 국경 두번 넘는 이유는?</a></div></div>","link":"https://www.bbc.com/korean/news-59856610","retrieved":1641402074935},{"title":"중국 축구 국가대표 '문신 금지령'...'문신 있으면 뽑지 말아라'","contents":"<div class=\"bbc-1k5dca0 emesykt1\"><div dir=\"ltr\" class=\"bbc-cco6mt erh4ywh3\"><span class=\"bbc-1kpt1ox erh4ywh0\">10</span></div><div dir=\"ltr\" class=\"bbc-1dy6y1w emesykt3\"><a href=\"/korean/international-59807505\" class=\"bbc-bta7jm emesykt4\">중국 축구 국가대표 '문신 금지령'...'문신 있으면 뽑지 말아라'</a></div></div>","link":"https://www.bbc.com/korean/international-59807505","retrieved":1641402074936}]}